fact_blitz/__init__.py
fact_blitz/__main__.py
fact_blitz/assets/fun_facts_10000.csv
fact_blitz/assets/video_backgrounds/fixed_video.mp4
fact_blitz/assets/video_backgrounds/video_background.mp4
fun_fact/__init__.py
fun_fact/fun_fact_urls.py
fun_fact/scraper.py
fun_fact/web_driver.py
tiktok/__init__.py
tiktok/upload.py
video_editor/__init__.py
video_editor/overlay.py
video_editor/voice_generator.py
youtube/__init__.py
youtube/download_funtions.py
youtube/upload.py
youtube/video_urls.py
factblitz-0.0.1.dist-info/METADATA
factblitz-0.0.1.dist-info/WHEEL
factblitz-0.0.1.dist-info/entry_points.txt
factblitz-0.0.1.dist-info/top_level.txt
factblitz-0.0.1.dist-info/RECORD
